<?xml version="1.0" encoding="utf-8"?><Root xmlns:xsd="http://www.w3.org/2001/XMLSchema" xmlns:xsi="http://www.w3.org/2001/XMLSchema-instance"><States><State Code="MD"><Cities><City><Name>Rockville</Name><State>Maryland</State><Code>20850</Code><Checked>false</Checked></City><City><Name>Baltimore</Name><State>Maryland</State><Code>21201</Code><Checked>false</Checked></City><City><Name>Hagerstown</Name><State>Maryland</State><Code>21740</Code><Checked>false</Checked></City><City><Name>Waldorf</Name><State>Maryland</State><Code>20601</Code><Checked>false</Checked></City><City><Name>Waldorf</Name><State>Maryland</State><Code>20602</Code><Checked>false</Checked></City><City><Name>Waldorf</Name><State>Maryland</State><Code>20603</Code><Checked>false</Checked></City><City><Name>Waldorf</Name><State>Maryland</State><Code>20604</Code><Checked>false</Checked></City><City><Name>Abell</Name><State>Maryland</State><Code>20606</Code><Checked>false</Checked></City><City><Name>Accokeek</Name><State>Maryland</State><Code>20607</Code><Checked>false</Checked></City><City><Name>Aquasco</Name><State>Maryland</State><Code>20608</Code><Checked>false</Checked></City><City><Name>Avenue</Name><State>Maryland</State><Code>20609</Code><Checked>false</Checked></City><City><Name>Barstow</Name><State>Maryland</State><Code>20610</Code><Checked>false</Checked></City><City><Name>Bel Alton</Name><State>Maryland</State><Code>20611</Code><Checked>false</Checked></City><City><Name>Benedict</Name><State>Maryland</State><Code>20612</Code><Checked>false</Checked></City><City><Name>Brandywine</Name><State>Maryland</State><Code>20613</Code><Checked>false</Checked></City><City><Name>Broomes Island</Name><State>Maryland</State><Code>20615</Code><Checked>false</Checked></City><City><Name>Bryans Road</Name><State>Maryland</State><Code>20616</Code><Checked>false</Checked></City><City><Name>Bryantown</Name><State>Maryland</State><Code>20617</Code><Checked>false</Checked></City><City><Name>Bushwood</Name><State>Maryland</State><Code>20618</Code><Checked>false</Checked></City><City><Name>California</Name><State>Maryland</State><Code>20619</Code><Checked>false</Checked></City><City><Name>Callaway</Name><State>Maryland</State><Code>20620</Code><Checked>false</Checked></City><City><Name>Chaptico</Name><State>Maryland</State><Code>20621</Code><Checked>false</Checked></City><City><Name>Charlotte Hall</Name><State>Maryland</State><Code>20622</Code><Checked>false</Checked></City><City><Name>Cheltenham</Name><State>Maryland</State><Code>20623</Code><Checked>false</Checked></City><City><Name>Clements</Name><State>Maryland</State><Code>20624</Code><Checked>false</Checked></City><City><Name>Cobb Island</Name><State>Maryland</State><Code>20625</Code><Checked>false</Checked></City><City><Name>Coltons Point</Name><State>Maryland</State><Code>20626</Code><Checked>false</Checked></City><City><Name>Compton</Name><State>Maryland</State><Code>20627</Code><Checked>false</Checked></City><City><Name>Dameron</Name><State>Maryland</State><Code>20628</Code><Checked>false</Checked></City><City><Name>Dowell</Name><State>Maryland</State><Code>20629</Code><Checked>false</Checked></City><City><Name>Drayden</Name><State>Maryland</State><Code>20630</Code><Checked>false</Checked></City><City><Name>Faulkner</Name><State>Maryland</State><Code>20632</Code><Checked>false</Checked></City><City><Name>Great Mills</Name><State>Maryland</State><Code>20634</Code><Checked>false</Checked></City><City><Name>Helen</Name><State>Maryland</State><Code>20635</Code><Checked>false</Checked></City><City><Name>Hollywood</Name><State>Maryland</State><Code>20636</Code><Checked>false</Checked></City><City><Name>Hughesville</Name><State>Maryland</State><Code>20637</Code><Checked>false</Checked></City><City><Name>Huntingtown</Name><State>Maryland</State><Code>20639</Code><Checked>false</Checked></City><City><Name>Indian Head</Name><State>Maryland</State><Code>20640</Code><Checked>false</Checked></City><City><Name>Ironsides</Name><State>Maryland</State><Code>20643</Code><Checked>false</Checked></City><City><Name>Issue</Name><State>Maryland</State><Code>20645</Code><Checked>false</Checked></City><City><Name>La Plata</Name><State>Maryland</State><Code>20646</Code><Checked>false</Checked></City><City><Name>Leonardtown</Name><State>Maryland</State><Code>20650</Code><Checked>false</Checked></City><City><Name>Lexington Park</Name><State>Maryland</State><Code>20653</Code><Checked>false</Checked></City><City><Name>Loveville</Name><State>Maryland</State><Code>20656</Code><Checked>false</Checked></City><City><Name>Lusby</Name><State>Maryland</State><Code>20657</Code><Checked>false</Checked></City><City><Name>Marbury</Name><State>Maryland</State><Code>20658</Code><Checked>false</Checked></City><City><Name>Mechanicsville</Name><State>Maryland</State><Code>20659</Code><Checked>false</Checked></City><City><Name>Morganza</Name><State>Maryland</State><Code>20660</Code><Checked>false</Checked></City><City><Name>Nanjemoy</Name><State>Maryland</State><Code>20662</Code><Checked>false</Checked></City><City><Name>Newburg</Name><State>Maryland</State><Code>20664</Code><Checked>false</Checked></City><City><Name>Park Hall</Name><State>Maryland</State><Code>20667</Code><Checked>false</Checked></City><City><Name>Patuxent River</Name><State>Maryland</State><Code>20670</Code><Checked>false</Checked></City><City><Name>Piney Point</Name><State>Maryland</State><Code>20674</Code><Checked>false</Checked></City><City><Name>Pomfret</Name><State>Maryland</State><Code>20675</Code><Checked>false</Checked></City><City><Name>Port Republic</Name><State>Maryland</State><Code>20676</Code><Checked>false</Checked></City><City><Name>Port Tobacco</Name><State>Maryland</State><Code>20677</Code><Checked>false</Checked></City><City><Name>Prince Frederick</Name><State>Maryland</State><Code>20678</Code><Checked>false</Checked></City><City><Name>Ridge</Name><State>Maryland</State><Code>20680</Code><Checked>false</Checked></City><City><Name>Rock Point</Name><State>Maryland</State><Code>20682</Code><Checked>false</Checked></City><City><Name>Saint Marys City</Name><State>Maryland</State><Code>20686</Code><Checked>false</Checked></City><City><Name>Scotland</Name><State>Maryland</State><Code>20687</Code><Checked>false</Checked></City><City><Name>Solomons</Name><State>Maryland</State><Code>20688</Code><Checked>false</Checked></City><City><Name>Sunderland</Name><State>Maryland</State><Code>20689</Code><Checked>false</Checked></City><City><Name>Tall Timbers</Name><State>Maryland</State><Code>20690</Code><Checked>false</Checked></City><City><Name>Valley Lee</Name><State>Maryland</State><Code>20692</Code><Checked>false</Checked></City><City><Name>Welcome</Name><State>Maryland</State><Code>20693</Code><Checked>false</Checked></City><City><Name>White Plains</Name><State>Maryland</State><Code>20695</Code><Checked>false</Checked></City><City><Name>Annapolis Junction</Name><State>Maryland</State><Code>20701</Code><Checked>false</Checked></City><City><Name>Lanham</Name><State>Maryland</State><Code>20703</Code><Checked>false</Checked></City><City><Name>Beltsville</Name><State>Maryland</State><Code>20704</Code><Checked>false</Checked></City><City><Name>Beltsville</Name><State>Maryland</State><Code>20705</Code><Checked>false</Checked></City><City><Name>Lanham</Name><State>Maryland</State><Code>20706</Code><Checked>false</Checked></City><City><Name>Laurel</Name><State>Maryland</State><Code>20707</Code><Checked>false</Checked></City><City><Name>Laurel</Name><State>Maryland</State><Code>20708</Code><Checked>false</Checked></City><City><Name>Bladensburg</Name><State>Maryland</State><Code>20710</Code><Checked>false</Checked></City><City><Name>Lothian</Name><State>Maryland</State><Code>20711</Code><Checked>false</Checked></City><City><Name>North Beach</Name><State>Maryland</State><Code>20714</Code><Checked>false</Checked></City><City><Name>Bowie</Name><State>Maryland</State><Code>20715</Code><Checked>false</Checked></City><City><Name>Bowie</Name><State>Maryland</State><Code>20716</Code><Checked>false</Checked></City><City><Name>Bowie</Name><State>Maryland</State><Code>20717</Code><Checked>false</Checked></City><City><Name>Bowie</Name><State>Maryland</State><Code>20718</Code><Checked>false</Checked></City><City><Name>Bowie</Name><State>Maryland</State><Code>20719</Code><Checked>false</Checked></City><City><Name>Bowie</Name><State>Maryland</State><Code>20720</Code><Checked>false</Checked></City><City><Name>Bowie</Name><State>Maryland</State><Code>20721</Code><Checked>false</Checked></City><City><Name>Brentwood</Name><State>Maryland</State><Code>20722</Code><Checked>false</Checked></City><City><Name>Laurel</Name><State>Maryland</State><Code>20723</Code><Checked>false</Checked></City><City><Name>Laurel</Name><State>Maryland</State><Code>20724</Code><Checked>false</Checked></City><City><Name>Laurel</Name><State>Maryland</State><Code>20725</Code><Checked>false</Checked></City><City><Name>Laurel</Name><State>Maryland</State><Code>20726</Code><Checked>false</Checked></City><City><Name>Capitol Heights</Name><State>Maryland</State><Code>20731</Code><Checked>false</Checked></City><City><Name>Chesapeake Beach</Name><State>Maryland</State><Code>20732</Code><Checked>false</Checked></City><City><Name>Churchton</Name><State>Maryland</State><Code>20733</Code><Checked>false</Checked></City><City><Name>Clinton</Name><State>Maryland</State><Code>20735</Code><Checked>false</Checked></City><City><Name>Owings</Name><State>Maryland</State><Code>20736</Code><Checked>false</Checked></City><City><Name>Riverdale</Name><State>Maryland</State><Code>20737</Code><Checked>false</Checked></City><City><Name>Riverdale</Name><State>Maryland</State><Code>20738</Code><Checked>false</Checked></City><City><Name>College Park</Name><State>Maryland</State><Code>20740</Code><Checked>false</Checked></City><City><Name>College Park</Name><State>Maryland</State><Code>20741</Code><Checked>false</Checked></City><City><Name>College Park</Name><State>Maryland</State><Code>20742</Code><Checked>false</Checked></City><City><Name>Capitol Heights</Name><State>Maryland</State><Code>20743</Code><Checked>false</Checked></City><City><Name>Fort Washington</Name><State>Maryland</State><Code>20744</Code><Checked>false</Checked></City><City><Name>Oxon Hill</Name><State>Maryland</State><Code>20745</Code><Checked>false</Checked></City><City><Name>Suitland</Name><State>Maryland</State><Code>20746</Code><Checked>false</Checked></City><City><Name>District Heights</Name><State>Maryland</State><Code>20747</Code><Checked>false</Checked></City><City><Name>Temple Hills</Name><State>Maryland</State><Code>20748</Code><Checked>false</Checked></City><City><Name>Fort Washington</Name><State>Maryland</State><Code>20749</Code><Checked>false</Checked></City><City><Name>Oxon Hill</Name><State>Maryland</State><Code>20750</Code><Checked>false</Checked></City><City><Name>Deale</Name><State>Maryland</State><Code>20751</Code><Checked>false</Checked></City><City><Name>Suitland</Name><State>Maryland</State><Code>20752</Code><Checked>false</Checked></City><City><Name>District Heights</Name><State>Maryland</State><Code>20753</Code><Checked>false</Checked></City><City><Name>Dunkirk</Name><State>Maryland</State><Code>20754</Code><Checked>false</Checked></City><City><Name>Temple Hills</Name><State>Maryland</State><Code>20757</Code><Checked>false</Checked></City><City><Name>Friendship</Name><State>Maryland</State><Code>20758</Code><Checked>false</Checked></City><City><Name>Fulton</Name><State>Maryland</State><Code>20759</Code><Checked>false</Checked></City><City><Name>Savage</Name><State>Maryland</State><Code>20763</Code><Checked>false</Checked></City><City><Name>Shady Side</Name><State>Maryland</State><Code>20764</Code><Checked>false</Checked></City><City><Name>Galesville</Name><State>Maryland</State><Code>20765</Code><Checked>false</Checked></City><City><Name>Glenn Dale</Name><State>Maryland</State><Code>20769</Code><Checked>false</Checked></City><City><Name>Greenbelt</Name><State>Maryland</State><Code>20770</Code><Checked>false</Checked></City><City><Name>Greenbelt</Name><State>Maryland</State><Code>20771</Code><Checked>false</Checked></City><City><Name>Upper Marlboro</Name><State>Maryland</State><Code>20772</Code><Checked>false</Checked></City><City><Name>Upper Marlboro</Name><State>Maryland</State><Code>20773</Code><Checked>false</Checked></City><City><Name>Upper Marlboro</Name><State>Maryland</State><Code>20774</Code><Checked>false</Checked></City><City><Name>Upper Marlboro</Name><State>Maryland</State><Code>20775</Code><Checked>false</Checked></City><City><Name>Harwood</Name><State>Maryland</State><Code>20776</Code><Checked>false</Checked></City><City><Name>Highland</Name><State>Maryland</State><Code>20777</Code><Checked>false</Checked></City><City><Name>West River</Name><State>Maryland</State><Code>20778</Code><Checked>false</Checked></City><City><Name>Tracys Landing</Name><State>Maryland</State><Code>20779</Code><Checked>false</Checked></City><City><Name>Hyattsville</Name><State>Maryland</State><Code>20781</Code><Checked>false</Checked></City><City><Name>Hyattsville</Name><State>Maryland</State><Code>20782</Code><Checked>false</Checked></City><City><Name>Hyattsville</Name><State>Maryland</State><Code>20787</Code><Checked>false</Checked></City><City><Name>Hyattsville</Name><State>Maryland</State><Code>20788</Code><Checked>false</Checked></City><City><Name>Capitol Heights</Name><State>Maryland</State><Code>20790</Code><Checked>false</Checked></City><City><Name>Capitol Heights</Name><State>Maryland</State><Code>20791</Code><Checked>false</Checked></City><City><Name>Jessup</Name><State>Maryland</State><Code>20794</Code><Checked>false</Checked></City><City><Name>Glen Echo</Name><State>Maryland</State><Code>20812</Code><Checked>false</Checked></City><City><Name>Bethesda</Name><State>Maryland</State><Code>20814</Code><Checked>false</Checked></City><City><Name>Chevy Chase</Name><State>Maryland</State><Code>20815</Code><Checked>false</Checked></City><City><Name>Bethesda</Name><State>Maryland</State><Code>20816</Code><Checked>false</Checked></City><City><Name>Bethesda</Name><State>Maryland</State><Code>20817</Code><Checked>false</Checked></City><City><Name>Cabin John</Name><State>Maryland</State><Code>20818</Code><Checked>false</Checked></City><City><Name>Bethesda</Name><State>Maryland</State><Code>20824</Code><Checked>false</Checked></City><City><Name>Olney</Name><State>Maryland</State><Code>20830</Code><Checked>false</Checked></City><City><Name>Olney</Name><State>Maryland</State><Code>20832</Code><Checked>false</Checked></City><City><Name>Brookeville</Name><State>Maryland</State><Code>20833</Code><Checked>false</Checked></City><City><Name>Poolesville</Name><State>Maryland</State><Code>20837</Code><Checked>false</Checked></City><City><Name>Barnesville</Name><State>Maryland</State><Code>20838</Code><Checked>false</Checked></City><City><Name>Beallsville</Name><State>Maryland</State><Code>20839</Code><Checked>false</Checked></City><City><Name>Boyds</Name><State>Maryland</State><Code>20841</Code><Checked>false</Checked></City><City><Name>Dickerson</Name><State>Maryland</State><Code>20842</Code><Checked>false</Checked></City><City><Name>Rockville</Name><State>Maryland</State><Code>20847</Code><Checked>false</Checked></City><City><Name>Rockville</Name><State>Maryland</State><Code>20848</Code><Checked>false</Checked></City><City><Name>Rockville</Name><State>Maryland</State><Code>20849</Code><Checked>false</Checked></City><City><Name>Rockville</Name><State>Maryland</State><Code>20851</Code><Checked>false</Checked></City><City><Name>Rockville</Name><State>Maryland</State><Code>20852</Code><Checked>false</Checked></City><City><Name>Rockville</Name><State>Maryland</State><Code>20853</Code><Checked>false</Checked></City><City><Name>Potomac</Name><State>Maryland</State><Code>20854</Code><Checked>false</Checked></City><City><Name>Derwood</Name><State>Maryland</State><Code>20855</Code><Checked>false</Checked></City><City><Name>Rockville</Name><State>Maryland</State><Code>20857</Code><Checked>false</Checked></City><City><Name>Potomac</Name><State>Maryland</State><Code>20859</Code><Checked>false</Checked></City><City><Name>Sandy Spring</Name><State>Maryland</State><Code>20860</Code><Checked>false</Checked></City><City><Name>Ashton</Name><State>Maryland</State><Code>20861</Code><Checked>false</Checked></City><City><Name>Brinklow</Name><State>Maryland</State><Code>20862</Code><Checked>false</Checked></City><City><Name>Burtonsville</Name><State>Maryland</State><Code>20866</Code><Checked>false</Checked></City><City><Name>Spencerville</Name><State>Maryland</State><Code>20868</Code><Checked>false</Checked></City><City><Name>Clarksburg</Name><State>Maryland</State><Code>20871</Code><Checked>false</Checked></City><City><Name>Damascus</Name><State>Maryland</State><Code>20872</Code><Checked>false</Checked></City><City><Name>Germantown</Name><State>Maryland</State><Code>20874</Code><Checked>false</Checked></City><City><Name>Germantown</Name><State>Maryland</State><Code>20875</Code><Checked>false</Checked></City><City><Name>Germantown</Name><State>Maryland</State><Code>20876</Code><Checked>false</Checked></City><City><Name>Gaithersburg</Name><State>Maryland</State><Code>20877</Code><Checked>false</Checked></City><City><Name>Gaithersburg</Name><State>Maryland</State><Code>20878</Code><Checked>false</Checked></City><City><Name>Gaithersburg</Name><State>Maryland</State><Code>20879</Code><Checked>false</Checked></City><City><Name>Washington Grove</Name><State>Maryland</State><Code>20880</Code><Checked>false</Checked></City><City><Name>Gaithersburg</Name><State>Maryland</State><Code>20882</Code><Checked>false</Checked></City><City><Name>Gaithersburg</Name><State>Maryland</State><Code>20884</Code><Checked>false</Checked></City><City><Name>Gaithersburg</Name><State>Maryland</State><Code>20885</Code><Checked>false</Checked></City><City><Name>Montgomery Village</Name><State>Maryland</State><Code>20886</Code><Checked>false</Checked></City><City><Name>Bethesda</Name><State>Maryland</State><Code>20889</Code><Checked>false</Checked></City><City><Name>Kensington</Name><State>Maryland</State><Code>20891</Code><Checked>false</Checked></City><City><Name>Bethesda</Name><State>Maryland</State><Code>20892</Code><Checked>false</Checked></City><City><Name>Bethesda</Name><State>Maryland</State><Code>20894</Code><Checked>false</Checked></City><City><Name>Kensington</Name><State>Maryland</State><Code>20895</Code><Checked>false</Checked></City><City><Name>Garrett Park</Name><State>Maryland</State><Code>20896</Code><Checked>false</Checked></City><City><Name>Gaithersburg</Name><State>Maryland</State><Code>20898</Code><Checked>false</Checked></City><City><Name>Gaithersburg</Name><State>Maryland</State><Code>20899</Code><Checked>false</Checked></City><City><Name>Silver Spring</Name><State>Maryland</State><Code>20901</Code><Checked>false</Checked></City><City><Name>Silver Spring</Name><State>Maryland</State><Code>20902</Code><Checked>false</Checked></City><City><Name>Silver Spring</Name><State>Maryland</State><Code>20903</Code><Checked>false</Checked></City><City><Name>Silver Spring</Name><State>Maryland</State><Code>20904</Code><Checked>false</Checked></City><City><Name>Silver Spring</Name><State>Maryland</State><Code>20906</Code><Checked>false</Checked></City><City><Name>Silver Spring</Name><State>Maryland</State><Code>20907</Code><Checked>false</Checked></City><City><Name>Silver Spring</Name><State>Maryland</State><Code>20908</Code><Checked>false</Checked></City><City><Name>Silver Spring</Name><State>Maryland</State><Code>20910</Code><Checked>false</Checked></City><City><Name>Silver Spring</Name><State>Maryland</State><Code>20911</Code><Checked>false</Checked></City><City><Name>Takoma Park</Name><State>Maryland</State><Code>20912</Code><Checked>false</Checked></City><City><Name>Silver Spring</Name><State>Maryland</State><Code>20914</Code><Checked>false</Checked></City><City><Name>Silver Spring</Name><State>Maryland</State><Code>20915</Code><Checked>false</Checked></City><City><Name>Aberdeen</Name><State>Maryland</State><Code>21001</Code><Checked>false</Checked></City><City><Name>Abingdon</Name><State>Maryland</State><Code>21009</Code><Checked>false</Checked></City></Cities></State></States></Root>